{"version": "1", "message": "ERROR: Hidden Testcases server unreachable.", "problem_id": "ads2_m3_a1_1", "user_id": "vamshi0997", "score": {"sample": {"0": {"execution_time": 0.41206812858581543, "passed": true}, "1": {"execution_time": 0.3025999069213867, "passed": true}, "2": {"execution_time": 0.32950782775878906, "passed": true}, "3": {"execution_time": 0.3013017177581787, "passed": true}, "4": {"execution_time": 0.33307814598083496, "passed": true}, "5": {"execution_time": 0.2899608612060547, "passed": true}, "6": {"execution_time": 0.3401927947998047, "passed": true}, "7": {"execution_time": 0.27782678604125977, "passed": true}}}, "check_style_score": "0/1"}