{"version": "1", "message": "ERROR: Hidden Testcases server unreachable.", "problem_id": "ads2_m14_a1_1", "user_id": "vamshi0997", "score": {"sample": {"0": {"execution_time": 0.6172947883605957, "passed": true}, "1": {"execution_time": 0.5520932674407959, "passed": true}, "2": {"execution_time": 0.4998457431793213, "passed": true}, "3": {"execution_time": 0.5138950347900391, "passed": true}, "4": {"execution_time": 0.4978179931640625, "passed": true}, "5": {"execution_time": 0.5090630054473877, "passed": true}}}, "check_style_score": "1/1"}